compose_py/__init__.py
compose_py/_types.py
compose_py/_version.py
compose_py/_yaml.py
compose_py/dumper.py
compose_py/loader.py
compose_py/model_type.py
compose_py/py.typed
compose_py/models_dataclasses/__init__.py
compose_py/models_dataclasses/_generated.py
compose_py/models_pydantic/__init__.py
compose_py/models_pydantic/_generated.py
compose_py-0.3.0.dist-info/LICENSE
compose_py-0.3.0.dist-info/METADATA
compose_py-0.3.0.dist-info/WHEEL
compose_py-0.3.0.dist-info/top_level.txt
compose_py-0.3.0.dist-info/RECORD
