Metadata-Version: 2.1
Name: compose-py
Version: 0.3.0
Summary: A Python library for parsing and loading Compose files
Author-email: Yuki Igarashi <me@bonprosoft.com>
License: MIT License
Project-URL: homepage, https://github.com/bonprosoft/compose-py
Project-URL: repository, https://github.com/bonprosoft/compose-py
Classifier: Programming Language :: Python :: 3
Classifier: Programming Language :: Python
Classifier: License :: OSI Approved :: MIT License
Requires-Python: >=3.6
License-File: LICENSE
Requires-Dist: PyYAML (>=5.1)
Provides-Extra: dataclasses
Requires-Dist: dacite (>=1.0) ; extra == 'dataclasses'
Provides-Extra: dev
Requires-Dist: black (==23.3.0) ; extra == 'dev'
Requires-Dist: datamodel-code-generator (==0.19.0) ; extra == 'dev'
Requires-Dist: flake8 (==6.0.0) ; extra == 'dev'
Requires-Dist: isort (==5.12.0) ; extra == 'dev'
Requires-Dist: mypy (==1.3.0) ; extra == 'dev'
Requires-Dist: pysen (==0.10.4) ; extra == 'dev'
Requires-Dist: pytest (==7.3.1) ; extra == 'dev'
Requires-Dist: types-PyYAML (==6.0.12.9) ; extra == 'dev'
Provides-Extra: pydantic
Requires-Dist: pydantic ; extra == 'pydantic'
